KaiRoS/__init__.py
KaiRoS/reference.py
KaiRoS/terminal.py
KaiRoS/utils.py
KaiRoS/weather.py
wkairos-0.0.0.3.data/scripts/kairos
wkairos-0.0.0.3.dist-info/LICENSE
wkairos-0.0.0.3.dist-info/METADATA
wkairos-0.0.0.3.dist-info/WHEEL
wkairos-0.0.0.3.dist-info/top_level.txt
wkairos-0.0.0.3.dist-info/RECORD
