Metadata-Version: 2.1
Name: wkairos
Version: 0.0.0.3
Summary: A command line weather app.
Home-page: https://github.com/MutatedFlood/KaiRoS
Author: MutatedFlood
Author-email: b06901038@g.ntu.edu.tw
License: MIT
Keywords: weather
Platform: UNKNOWN
Classifier: Programming Language :: Python :: 3
Classifier: License :: OSI Approved :: MIT License
Classifier: Operating System :: OS Independent
Requires-Dist: requests
